.bumpversion.cfg
MANIFEST.in
README.md
pypackage.mk
requirements.txt
setup.py
src/comptests/__init__.py
src/comptests/comptest_to_junit.py
src/comptests/comptests.py
src/comptests/find_modules_imp.py
src/comptests/nose.py
src/comptests/registrar.py
src/comptests/reports.py
src/comptests/results.py
src/comptests/unittests/__init__.py
src/comptests/unittests/test_example_package.py
src/comptests_ex/__init__.py
src/comptests_ex/test_yield.py
src/comptests_z6.egg-info/PKG-INFO
src/comptests_z6.egg-info/SOURCES.txt
src/comptests_z6.egg-info/dependency_links.txt
src/comptests_z6.egg-info/entry_points.txt
src/comptests_z6.egg-info/requires.txt
src/comptests_z6.egg-info/top_level.txt
src/example_package/__init__.py
src/example_package/configuration.py
src/example_package/interfaces.py
src/example_package/unittests/__init__.py
src/example_package/unittests/all_tests.py
src/example_package/unittests/generation.py